odoo/addons/sale_analytic_distribution_model_warehouse/README.rst
odoo/addons/sale_analytic_distribution_model_warehouse/__init__.py
odoo/addons/sale_analytic_distribution_model_warehouse/__manifest__.py
odoo/addons/sale_analytic_distribution_model_warehouse/i18n/es.po
odoo/addons/sale_analytic_distribution_model_warehouse/i18n/it.po
odoo/addons/sale_analytic_distribution_model_warehouse/i18n/sale_analytic_distribution_model_warehouse.pot
odoo/addons/sale_analytic_distribution_model_warehouse/models/__init__.py
odoo/addons/sale_analytic_distribution_model_warehouse/models/analytic_distribution_model.py
odoo/addons/sale_analytic_distribution_model_warehouse/models/sale_order_line.py
odoo/addons/sale_analytic_distribution_model_warehouse/readme/CONFIGURE.md
odoo/addons/sale_analytic_distribution_model_warehouse/readme/CONTRIBUTORS.md
odoo/addons/sale_analytic_distribution_model_warehouse/readme/DESCRIPTION.md
odoo/addons/sale_analytic_distribution_model_warehouse/readme/USAGE.md
odoo/addons/sale_analytic_distribution_model_warehouse/static/description/icon.png
odoo/addons/sale_analytic_distribution_model_warehouse/static/description/index.html
odoo/addons/sale_analytic_distribution_model_warehouse/tests/__init__.py
odoo/addons/sale_analytic_distribution_model_warehouse/tests/test_so_analytic_by_warehouse.py
odoo_addon_sale_analytic_distribution_model_warehouse-18.0.1.0.1.3.dist-info/METADATA
odoo_addon_sale_analytic_distribution_model_warehouse-18.0.1.0.1.3.dist-info/WHEEL
odoo_addon_sale_analytic_distribution_model_warehouse-18.0.1.0.1.3.dist-info/top_level.txt
odoo_addon_sale_analytic_distribution_model_warehouse-18.0.1.0.1.3.dist-info/RECORD
