Metadata-Version: 2.1
Name: odoo-addon-sale_analytic_distribution_model_warehouse
Version: 18.0.1.0.1.3
Requires-Python: >=3.10
Requires-Dist: odoo==18.0.*
Summary: Use analytic distribution models based on the warehouse in sale orders
Home-page: https://github.com/OCA/account-analytic
License: AGPL-3
Author: Tecnativa, Odoo Community Association (OCA)
Author-email: support@odoo-community.org
Classifier: Programming Language :: Python
Classifier: Framework :: Odoo
Classifier: Framework :: Odoo :: 18.0
Classifier: License :: OSI Approved :: GNU Affero General Public License v3
